[{"id":"e5f07855-fcff-4141-9b3d-394d8d4f9286","name":"manuel","surname":"barzi","username":"mb","password":"123","postits":[{"id":"68d6d52c-29c2-4e08-aee2-9574f02582b1","text":"my post-it 2"},{"id":"f0ae412f-1278-455a-b229-9fc35cd3350a","text":"my new post-it 3"},{"id":"b9d50c81-036f-4a7d-8f4f-b9d33dd13a90","text":"my post-it 2"},{"id":"dbc97c8d-487f-409b-bf2a-65dc39aad153","text":"my post-it 2"}]},{"id":"cf1d3ae6-55a5-4194-8ee7-bf7569284946","name":"manuel","surname":"barzi","username":"mb_2","password":"123","postits":[]},{"id":"5f08456e-9b27-496a-9d6d-0504a9c5c44e","name":"carlos","surname":"diestro","username":"cd","password":"qwe","postits":[{"id":"5c4306e0-a49c-42f1-b656-1e39a06a7684","text":"my post-it"}]},{"id":"7b67fe63-aa80-4a52-9a32-762dc497c838","name":"John","surname":"Doe","username":"jd-0.1703193941681398","password":"123","postits":[]},{"id":"86dba8a0-6bd4-4ed6-9ac1-5e7506f250ee","name":"John","surname":"Doe","username":"jd-0.20373475088919935","password":"123","postits":[]},{"id":"1a864281-443b-48b9-864b-d9ab2c7b83c0","name":"John","surname":"Doe","username":"jd-0.2551448959404332","password":"123","postits":[]},{"id":"dc6fb36a-249a-4e84-a4b2-15644553cc5d","name":"John","surname":"Doe","username":"jd-0.23273019319505095","password":"123","postits":[]},{"id":"6c816d1c-d319-4c26-bb7e-5a9bfd39bfe7","name":"John","surname":"Doe","username":"jd-0.1899863879500283","password":"123-0.7536974959581049","postits":[]},{"id":"31593ab2-7d19-4ca5-95f5-430c3d47149f","name":"John","surname":"Doe","username":"jd-0.23425589019771964","password":"123-0.07367050083292637","postits":[]},{"id":"b3ccefbe-373d-4297-8b4a-813b2d992235","name":"John","surname":"Doe","username":"jd-0.009724961464477433","password":"123-0.14612149120822493","postits":[]},{"id":"334982f8-3032-42c6-899c-19671b19c3de","name":"John","surname":"Doe","username":"jd-0.18216402061110215","password":"123-0.18879850964501044","postits":[]},{"id":"b8000356-9a24-42e2-a175-bfaeea9a1c56","name":"John","surname":"Doe","username":"jd-0.027416899818161866","password":"123","postits":[]},{"id":"d9054f35-93b3-4298-a949-87dfb168c382","name":"John","surname":"Doe","username":"jd-0.499419439709915","password":"123","postits":[]},{"id":"fb8d1003-b084-4d37-85ec-86c73912bf38","name":"John","surname":"Doe","username":"jd-0.8457917712265144","password":"123-0.28294467121344935","postits":[]},{"id":"b4294330-d5ed-47d2-a36d-6e940e512258","name":"John","surname":"Doe","username":"jd-0.7411013793059844","password":"123","postits":[]},{"id":"135cc16f-c8dc-45b5-9cd7-39c4ed4646e8","name":"John","surname":"Doe","username":"jd-0.21196938678725474","password":"123","postits":[]},{"id":"6d33f631-7039-4525-857a-6df51832912d","name":"carlos","surname":"diestro","username":"cad","password":"qwe","postits":[]},{"id":"3881267e-54cd-41e0-acb6-40fad7d6f048","name":"John","surname":"Doe","username":"jd-0.28398608976065276","password":"123","postits":[]},{"id":"65eb54a9-4398-4d16-9d3b-6111d69ce822","name":"John","surname":"Doe","username":"jd-0.13455892689107762","password":"123","postits":[]},{"id":"76dca7fb-d1d4-4560-96e3-173d8a127bc2","name":"John","surname":"Doe","username":"jd-0.32812711914409176","password":"123","postits":[]}]